MANIFEST.in
README.rst
setup.cfg
setup.py
LaviRot/__init__.py
LaviRot/elements.py
LaviRot/results.py
LaviRot/rotor.py
LaviRot.egg-info/PKG-INFO
LaviRot.egg-info/SOURCES.txt
LaviRot.egg-info/dependency_links.txt
LaviRot.egg-info/top_level.txt
LaviRot/styles/custom.css
LaviRot/styles/matplotlibrc