Metadata-Version: 1.0
Name: LaviRot
Version: 0.1.4b0
Summary: LaviRot
Home-page: UNKNOWN
Author: Lavi
Author-email: raphaelts@gmail.com
License: UNKNOWN
Platform: UNKNOWN
